onekey_agent_router/__init__.py
onekey_agent_router/base.py
onekey_agent_router/cli.py
onekey_agent_router/config.py
onekey_agent_router/constants.py
onekey_agent_router/utils.py
onekey_agent_router-0.0.1.dist-info/METADATA
onekey_agent_router-0.0.1.dist-info/WHEEL
onekey_agent_router-0.0.1.dist-info/top_level.txt
onekey_agent_router-0.0.1.dist-info/RECORD
