Metadata-Version: 2.4
Name: onekey_agent_router
Version: 0.0.1
Summary: AI Agent Router to Call Various AI Agents Function Call from massive Agent/MCP/Tools Marketplace
Author: deepnlp.org
Author-email: aihubadmin@126.com
Project-URL: Homepage, https://www.deepnlp.org/store/ai-agent
Project-URL: Repository, https://github.com/aiagenta2z/agent_router
Project-URL: Documentation, https://deepnlp.org/doc/onekey_mcp_router
Requires-Python: >=3.11
Requires-Dist: requests>=2.28.1
Requires-Dist: logging>=0.0.1
